MutTui/__init__.py
MutTui/__main__.py
MutTui/add_tree_node_labels.py
MutTui/branch_labelling.py
MutTui/cluster_spectra.py
MutTui/combine_spectra.py
MutTui/combine_spectra_into_catalog.py
MutTui/compare_mutation_ratios.py
MutTui/compare_spectra.py
MutTui/convert_vcf_position_translation.py
MutTui/generate_enriched_spectrum.py
MutTui/gff_conversion.py
MutTui/isvalid.py
MutTui/korimuto.py
MutTui/label_tree.py
MutTui/label_tree_gene_mutations.py
MutTui/muttui.py
MutTui/plot_mutation_type_comparison.py
MutTui/plot_spectrum.py
MutTui/post_process_branch_mutations.py
MutTui/reconstruct_spectrum.py
MutTui/rescale_spectrum.py
MutTui/summarise_branch_mutations.py
MutTui/treetime.py
MutTui-2.0.2.dist-info/LICENSE
MutTui-2.0.2.dist-info/METADATA
MutTui-2.0.2.dist-info/WHEEL
MutTui-2.0.2.dist-info/entry_points.txt
MutTui-2.0.2.dist-info/top_level.txt
MutTui-2.0.2.dist-info/RECORD
